df_script_parser/__init__.py
df_script_parser/cli.py
df_script_parser/dumpers_loaders.py
df_script_parser/tools.py
df_script_parser/processors/__init__.py
df_script_parser/processors/dict_processors.py
df_script_parser/processors/parse.py
df_script_parser/processors/recursive_parser.py
df_script_parser/utils/__init__.py
df_script_parser/utils/code_wrappers.py
df_script_parser/utils/convenience_functions.py
df_script_parser/utils/exceptions.py
df_script_parser/utils/module_metadata.py
df_script_parser/utils/namespaces.py
df_script_parser/utils/validators.py
df_script_parser-0.2.0.dist-info/LICENSE
df_script_parser-0.2.0.dist-info/METADATA
df_script_parser-0.2.0.dist-info/WHEEL
df_script_parser-0.2.0.dist-info/entry_points.txt
df_script_parser-0.2.0.dist-info/top_level.txt
df_script_parser-0.2.0.dist-info/RECORD
