Metadata-Version: 2.1
Name: df-script-parser
Version: 0.2.0
Summary: **Dialog Flow Script Parser** is python module add-on for [Dialog Flow Framework](https://github.com/deeppavlovteam/dialog_flow_framework), a free and open-source software stack for creating chatbots, released under the terms of Apache License 2.0.
Home-page: https://github.com/deeppavlovteam/dialog_flow_parser
Author: Denis Kuznetsov
Author-email: kuznetsov.den.p@gmail.com
Keywords: chatbots,Dialog Flow Script Parser
Classifier: Development Status :: 2 - Pre-Alpha
Classifier: Intended Audience :: Developers
Classifier: Topic :: Software Development :: Build Tools
Classifier: License :: OSI Approved :: Apache Software License
Classifier: Operating System :: OS Independent
Classifier: Programming Language :: Python :: 3
Classifier: Programming Language :: Python :: 3.6
Classifier: Programming Language :: Python :: 3.7
Classifier: Programming Language :: Python :: 3.8
Classifier: Programming Language :: Python :: 3.9
Classifier: Programming Language :: Python :: 3 :: Only
Requires-Python: >=3.6, <4
License-File: LICENSE
Requires-Dist: libcst (>=0.4.1)
Requires-Dist: ruamel.yaml (>=0.17.21)
Requires-Dist: pyflakes (>=2.3.1)
Requires-Dist: black (>=20.8b1)
Requires-Dist: df-engine
Requires-Dist: types-setuptools
